{
    "Encoding": "UTF-8",
    "KPlugin": {
        "Authors": [
            {
                "Email": "albertvaka@gmail.com",
                "Name": "Albert Vaca",
                "Name[x-test]": "xxAlbert Vacaxx"
            }
        ],
        "Description": "Receive and send files, URLs or plain text easily",
        "Description[nl]": "Bestanden, URL's of platte tekst gemakkelijk ontvangen en verzenden",
        "Description[pt]": "Receber e enviar ficheiros, URL's ou texto normal de forma simples",
        "Description[sv]": "Ta emot och skicka filer, webbadresser eller vanlig text enkelt",
        "Description[x-test]": "xxReceive and send files, URLs or plain text easilyxx",
        "EnabledByDefault": true,
        "Icon": "folder-network",
        "Id": "kdeconnect_share",
        "License": "GPL",
        "Name": "Share and receive",
        "Name[nl]": "Delen en ontvangen",
        "Name[pt]": "Partilhar e receber",
        "Name[sv]": "Dela och ta emot",
        "Name[x-test]": "xxShare and receivexx",
        "ServiceTypes": [
            "KdeConnect/Plugin"
        ],
        "Version": "0.1",
        "Website": "http://albertvaka.wordpress.com"
    },
    "X-KdeConnect-OutgoingPackageType": [
        "kdeconnect.share.request"
    ],
    "X-KdeConnect-SupportedPackageType": [
        "kdeconnect.share.request"
    ]
}
